manufacturingcpkppk/__init__.py
manufacturingcpkppk/analysis.py
manufacturingcpkppk/data_import.py
manufacturingcpkppk/report.py
manufacturingcpkppk/util.py
manufacturingcpkppk/visual.py
manufacturingcpkppk-0.9.8.dist-info/METADATA
manufacturingcpkppk-0.9.8.dist-info/WHEEL
manufacturingcpkppk-0.9.8.dist-info/top_level.txt
manufacturingcpkppk-0.9.8.dist-info/RECORD
