Metadata-Version: 2.1
Name: manufacturingcpkppk
Version: 0.9.8
Summary: manufacturingcpkppk data for trends, Cpk/Ppk.
Home-page: https://github.com/ahmadbelb/manf
Author: Ahmad M. Belbeisi
Author-email: ahmadbelb@gmail.com
License: UNKNOWN
Platform: UNKNOWN
Classifier: Programming Language :: Python :: 3
Classifier: License :: OSI Approved :: MIT License
Classifier: Operating System :: OS Independent
Requires-Python: >=3.6
